graphene_django/__init__.py
graphene_django/compat.py
graphene_django/conftest.py
graphene_django/constants.py
graphene_django/converter.py
graphene_django/fields.py
graphene_django/registry.py
graphene_django/settings.py
graphene_django/types.py
graphene_django/views.py
graphene_django/debug/__init__.py
graphene_django/debug/middleware.py
graphene_django/debug/types.py
graphene_django/debug/exception/__init__.py
graphene_django/debug/exception/formating.py
graphene_django/debug/exception/types.py
graphene_django/debug/sql/__init__.py
graphene_django/debug/sql/tracking.py
graphene_django/debug/sql/types.py
graphene_django/debug/tests/__init__.py
graphene_django/debug/tests/test_query.py
graphene_django/filter/__init__.py
graphene_django/filter/fields.py
graphene_django/filter/filterset.py
graphene_django/filter/utils.py
graphene_django/filter/filters/__init__.py
graphene_django/filter/filters/array_filter.py
graphene_django/filter/filters/global_id_filter.py
graphene_django/filter/filters/list_filter.py
graphene_django/filter/filters/range_filter.py
graphene_django/filter/filters/typed_filter.py
graphene_django/filter/tests/__init__.py
graphene_django/filter/tests/conftest.py
graphene_django/filter/tests/filters.py
graphene_django/filter/tests/test_array_field_contains_filter.py
graphene_django/filter/tests/test_array_field_custom_filter.py
graphene_django/filter/tests/test_array_field_exact_filter.py
graphene_django/filter/tests/test_array_field_overlap_filter.py
graphene_django/filter/tests/test_enum_filtering.py
graphene_django/filter/tests/test_fields.py
graphene_django/filter/tests/test_in_filter.py
graphene_django/filter/tests/test_range_filter.py
graphene_django/filter/tests/test_typed_filter.py
graphene_django/forms/__init__.py
graphene_django/forms/converter.py
graphene_django/forms/forms.py
graphene_django/forms/mutation.py
graphene_django/forms/types.py
graphene_django/forms/tests/__init__.py
graphene_django/forms/tests/test_converter.py
graphene_django-3.2.2.dist-info/LICENSE
graphene_django-3.2.2.dist-info/METADATA
graphene_django-3.2.2.dist-info/WHEEL
graphene_django-3.2.2.dist-info/top_level.txt
graphene_django-3.2.2.dist-info/RECORD
