Metadata-Version: 2.1
Name: graphene-django
Version: 3.2.2
Summary: Graphene Django integration
Home-page: https://github.com/graphql-python/graphene-django
Author: Syrus Akbary
Author-email: me@syrusakbary.com
License: MIT
Keywords: api graphql protocol rest relay graphene
Platform: any
Classifier: Development Status :: 5 - Production/Stable
Classifier: Intended Audience :: Developers
Classifier: Topic :: Software Development :: Libraries
Classifier: Programming Language :: Python :: 3
Classifier: Programming Language :: Python :: 3.8
Classifier: Programming Language :: Python :: 3.9
Classifier: Programming Language :: Python :: 3.10
Classifier: Programming Language :: Python :: 3.11
Classifier: Programming Language :: Python :: 3.12
Classifier: Programming Language :: Python :: Implementation :: PyPy
Classifier: Framework :: Django
Classifier: Framework :: Django :: 3.2
Classifier: Framework :: Django :: 4.1
Classifier: Framework :: Django :: 4.2
Provides-Extra: test
Provides-Extra: rest_framework
Provides-Extra: dev
License-File: LICENSE
